wmb_browser/__init__.py
wmb_browser/foo.py
wmb_browser-0.0.1.dist-info/LICENSE
wmb_browser-0.0.1.dist-info/METADATA
wmb_browser-0.0.1.dist-info/WHEEL
wmb_browser-0.0.1.dist-info/RECORD
