Metadata-Version: 2.1
Name: wmb-browser
Version: 0.0.1
Summary: Whole Mouse Brain Browser
Home-page: https://github.com/lhqing/wmb-browser
Author: Hanqing Liu
Author-email: fliuhanqing93@gmail.com
Requires-Python: >=3.9,<4.0
Classifier: Programming Language :: Python :: 3
Classifier: Programming Language :: Python :: 3.9
Classifier: Programming Language :: Python :: 3.10
Classifier: Programming Language :: Python :: 3.11
Requires-Dist: dash (>=2.9.2,<3.0.0)
Requires-Dist: pandas (==1.5.3)
Requires-Dist: xarray (>=2023.3.0,<2024.0.0)
Project-URL: Documentation, https://lhqing.github.io/wmb-browser/
Project-URL: Repository, https://github.com/lhqing/wmb-browser
